PythonCyc-2.0.2.data/data/examples/Operations_on_Compounds.ipynb
PythonCyc-2.0.2.data/data/examples/Operations_on_Enzymatic-Reactions.ipynb
PythonCyc-2.0.2.data/data/examples/Operations_on_Genes.ipynb
PythonCyc-2.0.2.data/data/examples/Operations_on_Pathways.ipynb
PythonCyc-2.0.2.data/data/examples/Operations_on_Proteins_and_Protein_Complexes.ipynb
PythonCyc-2.0.2.data/data/examples/Operations_on_Reactions.ipynb
PythonCyc-2.0.2.data/data/examples/Operations_on_Regulation_Frames.ipynb
PythonCyc-2.0.2.data/data/examples/enumeration_operations.ipynb
PythonCyc-2.0.2.dist-info/DESCRIPTION.rst
PythonCyc-2.0.2.dist-info/METADATA
PythonCyc-2.0.2.dist-info/RECORD
PythonCyc-2.0.2.dist-info/WHEEL
PythonCyc-2.0.2.dist-info/metadata.json
PythonCyc-2.0.2.dist-info/top_level.txt
pythoncyc/PGDB.py
pythoncyc/PTools.py
pythoncyc/PToolsFrame.py
pythoncyc/__init__.py
pythoncyc/config.py
