Metadata-Version: 2.0
Name: PythonCyc
Version: 2.0.2
Summary: A Python interface to Pathway Tools, 2019 update
Home-page: https://github.com/networkbiolab/PythonCyc
Author: Rodrigo Santibáñez
Author-email: glucksfall@users.noreply.github.com
License: SRI International
Project-URL: Manual, https://pythoncyc-v20.readthedocs.io
Project-URL: Bug Reports, https://github.com/networkbiolab/PythonCyc/issues
Project-URL: Source, https://github.com/networkbiolab/PythonCyc
Platform: UNKNOWN
Requires-Python: ~=3.0
